{
  "lastUpdated": "2026-03-23T21:07:22.660798+00:00",
  "sources": [
    "spotify"
  ],
  "tracks": [
    {
      "name": "Better",
      "artist": "Khalid",
      "album": "Suncity",
      "image": "https://i.scdn.co/image/ab67616d0000b273316e987210a1186c95eff23e",
      "playedAt": "2026-01-28T04:38:05.432Z",
      "source": "spotify",
      "spotifyId": "6zeeWid2sgw4lap2jV61PZ",
      "nowPlaying": false
    },
    {
      "name": "Choomantar",
      "artist": "Sohail Sen, Benny Dayal, Aditi Singh Sharma, Irshad Kamil",
      "album": "Mere Brother Ki Dulhan",
      "image": "https://i.scdn.co/image/ab67616d0000b273a2011a6b7f81c63c1557076d",
      "playedAt": "2026-01-28T04:22:21.817Z",
      "source": "spotify",
      "spotifyId": "3JbujPTeag5mDMAcye3vDD",
      "nowPlaying": false
    },
    {
      "name": "Voh Dekhnay Mein",
      "artist": "Ali Zafar",
      "album": "London, Paris, New York (Original Motion Picture Soundtrack)",
      "image": "https://i.scdn.co/image/ab67616d0000b273d9168a716dd978d5322f411a",
      "playedAt": "2026-01-20T22:39:06.921Z",
      "source": "spotify",
      "spotifyId": "0EMYTe2oQy70PCKPQFlbVy",
      "nowPlaying": false
    },
    {
      "name": "Rakhlo Tum Chupaake",
      "artist": "Arpit Bala, Adil",
      "album": "Keychain Laalu",
      "image": "https://i.scdn.co/image/ab67616d0000b273bc52b9838ebcfae5646a5457",
      "playedAt": "2026-01-20T06:07:03.618Z",
      "source": "spotify",
      "spotifyId": "5nXmr6ypbTYjhLR3lXSPyc",
      "nowPlaying": false
    },
    {
      "name": "Aadat",
      "artist": "Jal",
      "album": "Aadat (Remastered)",
      "image": "https://i.scdn.co/image/ab67616d0000b2737542aed098fc044db8ce8498",
      "playedAt": "2026-01-20T05:56:33.387Z",
      "source": "spotify",
      "spotifyId": "0lhlqmzeqlOCIgJH3yL6IY",
      "nowPlaying": false
    },
    {
      "name": "Woh Ladki Hai Kahan",
      "artist": "Shaan, Kavita Krishnamurthy",
      "album": "Dil Chahta Hai",
      "image": "https://i.scdn.co/image/ab67616d0000b2735da5e18b4f9a33d42e737c21",
      "playedAt": "2026-01-07T11:25:35.220Z",
      "source": "spotify",
      "spotifyId": "2tO0QPdCA0jgDBshTuYYkc",
      "nowPlaying": false
    },
    {
      "name": "For A Reason",
      "artist": "Karan Aujla, Ikky",
      "album": "P-POP CULTURE",
      "image": "https://i.scdn.co/image/ab67616d0000b27389e8f71cb6f3b6cc60944858",
      "playedAt": "2026-01-07T11:20:01.510Z",
      "source": "spotify",
      "spotifyId": "0cYohCh24y1aMjJmcS9RBl",
      "nowPlaying": false
    },
    {
      "name": "Tumne Jab Zulf-e-Pareshan Ko Sanwara Hoga",
      "artist": "Ustad Jafar Badayuni",
      "album": "Tumne Jab Zulf-e-Pareshan Ko Sanwara Hoga",
      "image": "https://i.scdn.co/image/ab67616d0000b273beb05424c3e1c3e74b75214f",
      "playedAt": "2025-12-29T20:35:59.782Z",
      "source": "spotify",
      "spotifyId": "1maGNaWdI4GfoDOFc4BZxP",
      "nowPlaying": false
    },
    {
      "name": "Tujhe Bhula Diya",
      "artist": "Vishal-Shekhar, Mohit Chauhan, Shekhar Ravjiani, Shruti Pathak",
      "album": "Anjaana Anjaani",
      "image": "https://i.scdn.co/image/ab67616d0000b2731da0a37c5bad81580d49ef05",
      "playedAt": "2025-12-29T13:35:12.836Z",
      "source": "spotify",
      "spotifyId": "4r8JqkhpTb5tzSKKHnVJIJ",
      "nowPlaying": false
    }
  ]
}